{
  "model": [
    {
      "name": "ASHOK KUMAR",
      "party": "Bahujan Samaj Party",
      "state": "Jammu & Kashmir",
      "constituency": "Jammu",
      "data": {
      }
    },
    {
      "name": "JUGAL KISHORE",
      "party": "Bharatiya Janata Party",
      "state": "Jammu & Kashmir",
      "constituency": "Jammu",
      "data": {
      }
    },
    {
      "name": "MADAN LAL SHARMA",
      "party": "Indian National Congress",
      "state": "Jammu & Kashmir",
      "constituency": "Jammu",
      "data": {
      }
    },
    {
      "name": "HARI CHAND JALMERIA",
      "party": "Jammu & Kashmir National Panthers Party",
      "state": "Jammu & Kashmir",
      "constituency": "Jammu",
      "data": {
      }
    },
    {
      "name": "YASHPAL SHARMA",
      "party": "Jammu & Kashmir Peoples Democratic Party",
      "state": "Jammu & Kashmir",
      "constituency": "Jammu",
      "data": {
      }
    },
    {
      "name": "BAHADUR SINGH CHOWDHARY",
      "party": "Samajwadi Party",
      "state": "Jammu & Kashmir",
      "constituency": "Jammu",
      "data": {
      }
    },
    {
      "name": "SUBASH CHANDER",
      "party": "All J & K Kisan Majdoor Party",
      "state": "Jammu & Kashmir",
      "constituency": "Jammu",
      "data": {
      }
    },
    {
      "name": "GURSAGAR SINGH",
      "party": "Socialistic Democratic Party",
      "state": "Jammu & Kashmir",
      "constituency": "Jammu",
      "data": {
      }
    },
    {
      "name": "MEHAR MANAV BHAGAT",
      "party": "Bharatiya Bahujan Party",
      "state": "Jammu & Kashmir",
      "constituency": "Jammu",
      "data": {
      }
    },
    {
      "name": "ASHOK KUMAR SHARMA",
      "party": "Independent",
      "state": "Jammu & Kashmir",
      "constituency": "Jammu",
      "data": {
      }
    },
    {
      "name": "PERSEEN SINGH",
      "party": "Independent",
      "state": "Jammu & Kashmir",
      "constituency": "Jammu",
      "data": {
      }
    },
    {
      "name": "RAJ KUMAR",
      "party": "Independent",
      "state": "Jammu & Kashmir",
      "constituency": "Jammu",
      "data": {
      }
    },
    {
      "name": "SATISH POONCHI",
      "party": "Independent",
      "state": "Jammu & Kashmir",
      "constituency": "Jammu",
      "data": {
      }
    },
    {
      "name": "ABDUL MAJID CHOUHAN",
      "party": "Independent",
      "state": "Jammu & Kashmir",
      "constituency": "Jammu",
      "data": {
      }
    },
    {
      "name": "LABHA RAM",
      "party": "Independent",
      "state": "Jammu & Kashmir",
      "constituency": "Jammu",
      "data": {
      }
    },
    {
      "name": "MOHD. IMTIAZ",
      "party": "Independent",
      "state": "Jammu & Kashmir",
      "constituency": "Jammu",
      "data": {
      }
    },
    {
      "name": "MOHD. ABBAS KHAN",
      "party": "Independent",
      "state": "Jammu & Kashmir",
      "constituency": "Jammu",
      "data": {
      }
    },
    {
      "name": "NIRMAL SINGH",
      "party": "Independent",
      "state": "Jammu & Kashmir",
      "constituency": "Jammu",
      "data": {
      }
    },
    {
      "name": "VIJAY KUMAR",
      "party": "Independent",
      "state": "Jammu & Kashmir",
      "constituency": "Jammu",
      "data": {
      }
    }
  ]
}