{
  "model": [
    {
      "name": "D.K. (DEV KRISHAN) CHHANGANI",
      "party": "Communist Party of India",
      "state": "Rajasthan",
      "constituency": "Jaipur",
      "data": {
      }
    },
    {
      "name": "FAROOQ SHAH",
      "party": "Bahujan Samaj Party",
      "state": "Rajasthan",
      "constituency": "Jaipur",
      "data": {
      }
    },
    {
      "name": "DR. MAHESH JOSHI",
      "party": "Indian National Congress",
      "state": "Rajasthan",
      "constituency": "Jaipur",
      "data": {
      }
    },
    {
      "name": "RAMCHARAN BOHARA",
      "party": "Bharatiya Janata Party",
      "state": "Rajasthan",
      "constituency": "Jaipur",
      "data": {
      }
    },
    {
      "name": "ANIL KUMAR SHARMA",
      "party": "Jago Party",
      "state": "Rajasthan",
      "constituency": "Jaipur",
      "data": {
      }
    },
    {
      "name": "ABDUL AZIZ BHARTIYA",
      "party": "Rashtriya Ulama Council",
      "state": "Rajasthan",
      "constituency": "Jaipur",
      "data": {
      }
    },
    {
      "name": "IFTEKAR QURISHI",
      "party": "All India Forward Bloc",
      "state": "Rajasthan",
      "constituency": "Jaipur",
      "data": {
      }
    },
    {
      "name": "KAILASH CHAND SAINI",
      "party": "Hindustan Janta Party",
      "state": "Rajasthan",
      "constituency": "Jaipur",
      "data": {
      }
    },
    {
      "name": "DR. TANMAY",
      "party": "Indian Peoples Green Party",
      "state": "Rajasthan",
      "constituency": "Jaipur",
      "data": {
      }
    },
    {
      "name": "NEERU AGARWAL",
      "party": "National Unionist Zamindara Party",
      "state": "Rajasthan",
      "constituency": "Jaipur",
      "data": {
      }
    },
    {
      "name": "RAJU LAL BAIRWA",
      "party": "Ambedkarite Party of India",
      "state": "Rajasthan",
      "constituency": "Jaipur",
      "data": {
      }
    },
    {
      "name": "DR. VIRENDRA SINGH",
      "party": "Aam Aadmi Party",
      "state": "Rajasthan",
      "constituency": "Jaipur",
      "data": {
      }
    },
    {
      "name": "PAWAN SINGH SHEKHAWAT",
      "party": "Independent",
      "state": "Rajasthan",
      "constituency": "Jaipur",
      "data": {
      }
    },
    {
      "name": "MUNNA DASS DABODIA",
      "party": "Independent",
      "state": "Rajasthan",
      "constituency": "Jaipur",
      "data": {
      }
    },
    {
      "name": "RAM SINGH RAJ",
      "party": "Independent",
      "state": "Rajasthan",
      "constituency": "Jaipur",
      "data": {
      }
    },
    {
      "name": "HAFIZ KHAN VARASI",
      "party": "Independent",
      "state": "Rajasthan",
      "constituency": "Jaipur",
      "data": {
      }
    }
  ]
}